stdplusAwsHelpers/AwsConnectionFactory.py
stdplusAwsHelpers/__init__.py
stdplusAwsHelpers/asg.py
stdplusAwsHelpers/ec2.py
stdplusAwsHelpers-0.0.45.dist-info/LICENSE
stdplusAwsHelpers-0.0.45.dist-info/METADATA
stdplusAwsHelpers-0.0.45.dist-info/WHEEL
stdplusAwsHelpers-0.0.45.dist-info/entry_points.txt
stdplusAwsHelpers-0.0.45.dist-info/top_level.txt
stdplusAwsHelpers-0.0.45.dist-info/RECORD
