Metadata-Version: 2.1
Name: stdplusAwsHelpers
Version: 0.0.45
Summary: Helpers for boto3
Home-page: https://github.com/earlye/
Author: Early Ehlinger
Author-email: earlye+stdplus@gmail.com
License: MIT
Keywords: boto3
Platform: UNKNOWN
Classifier: Development Status :: 3 - Alpha
Classifier: Intended Audience :: Developers
Classifier: Topic :: Software Development :: Libraries :: Python Modules
Classifier: License :: OSI Approved :: MIT License
Classifier: Programming Language :: Python :: 3
Classifier: Programming Language :: Python :: 3.7
Requires-Dist: boto3
